aiofirebase
