Metadata-Version: 1.0
Name: aiofirebase
Version: 0.2.0
Summary: Asyncio Firebase client library
Home-page: https://github.com/billyshambrook/aiofirebase
Author: Billy Shambrook
Author-email: billy.shambrook@gmail.com
License: UNKNOWN
Keywords: firebase,asyncio,aiohttp
Platform: UNKNOWN
